common_fate_schema/__init__.py
common_fate_schema/provider/__init__.py
common_fate_schema/provider/v1alpha1.py
common_fate_schema/tests/__init__.py
common_fate_schema/tests/__snapshots__/v1alpha1_test/test_v1alpha1_example.json
common_fate_schema/tests/__snapshots__/v1alpha1_test/test_v1alpha1_example_no_provider.json
common_fate_schema/tests/__snapshots__/v1alpha1_test/test_v1alpha1_minimal.json
common_fate_schema/tests/v1alpha1_test.py
common_fate_schema-0.6.0.dist-info/WHEEL
common_fate_schema-0.6.0.dist-info/METADATA
common_fate_schema-0.6.0.dist-info/RECORD
